{"id":"..\\node_modules\\reactstrap\\es\\UncontrolledNavDropdown.js","dependencies":[{"name":"C:\\Users\\Full Stack Web 7\\Desktop\\EGERIA.V3\\client\\node_modules\\reactstrap\\package.json","includedInParent":true,"mtime":1554285303055},{"name":"C:\\Users\\Full Stack Web 7\\Desktop\\EGERIA.V3\\client\\package.json","includedInParent":true,"mtime":1554732204840},{"name":"C:\\Users\\Full Stack Web 7\\Desktop\\EGERIA.V3\\client\\.babelrc","includedInParent":true,"mtime":1554278467137},{"name":"@babel/runtime/helpers/esm/extends","loc":{"line":1,"column":21},"parent":"C:\\Users\\Full Stack Web 7\\Desktop\\EGERIA.V3\\client\\node_modules\\reactstrap\\es\\UncontrolledNavDropdown.js","resolved":"C:\\Users\\Full Stack Web 7\\Desktop\\EGERIA.V3\\client\\node_modules\\@babel\\runtime\\helpers\\esm\\extends.js"},{"name":"react","loc":{"line":2,"column":18},"parent":"C:\\Users\\Full Stack Web 7\\Desktop\\EGERIA.V3\\client\\node_modules\\reactstrap\\es\\UncontrolledNavDropdown.js","resolved":"C:\\Users\\Full Stack Web 7\\Desktop\\EGERIA.V3\\client\\node_modules\\react\\index.js"},{"name":"./utils","loc":{"line":3,"column":25},"parent":"C:\\Users\\Full Stack Web 7\\Desktop\\EGERIA.V3\\client\\node_modules\\reactstrap\\es\\UncontrolledNavDropdown.js","resolved":"C:\\Users\\Full Stack Web 7\\Desktop\\EGERIA.V3\\client\\node_modules\\reactstrap\\es\\utils.js"},{"name":"./UncontrolledDropdown","loc":{"line":4,"column":33},"parent":"C:\\Users\\Full Stack Web 7\\Desktop\\EGERIA.V3\\client\\node_modules\\reactstrap\\es\\UncontrolledNavDropdown.js","resolved":"C:\\Users\\Full Stack Web 7\\Desktop\\EGERIA.V3\\client\\node_modules\\reactstrap\\es\\UncontrolledDropdown.js"}],"generated":{"js":"'use strict';\n\nObject.defineProperty(exports, \"__esModule\", {\n  value: true\n});\n\nvar _extends2 = require('@babel/runtime/helpers/esm/extends');\n\nvar _extends3 = _interopRequireDefault(_extends2);\n\nvar _react = require('react');\n\nvar _react2 = _interopRequireDefault(_react);\n\nvar _utils = require('./utils');\n\nvar _UncontrolledDropdown = require('./UncontrolledDropdown');\n\nvar _UncontrolledDropdown2 = _interopRequireDefault(_UncontrolledDropdown);\n\nfunction _interopRequireDefault(obj) { return obj && obj.__esModule ? obj : { default: obj }; }\n\nvar UncontrolledNavDropdown = function UncontrolledNavDropdown(props) {\n  (0, _utils.warnOnce)('The \"UncontrolledNavDropdown\" component has been deprecated.\\nPlease use component \"UncontrolledDropdown\" with nav prop.');\n  return _react2.default.createElement(_UncontrolledDropdown2.default, (0, _extends3.default)({\n    nav: true\n  }, props));\n};\n\nexports.default = UncontrolledNavDropdown;","map":{"mappings":[{"generated":{"line":7,"column":0},"source":"..\\node_modules\\reactstrap\\es\\UncontrolledNavDropdown.js","original":{"line":1,"column":0}},{"generated":{"line":11,"column":0},"source":"..\\node_modules\\reactstrap\\es\\UncontrolledNavDropdown.js","original":{"line":2,"column":0}},{"generated":{"line":15,"column":0},"source":"..\\node_modules\\reactstrap\\es\\UncontrolledNavDropdown.js","original":{"line":3,"column":0}},{"generated":{"line":17,"column":0},"source":"..\\node_modules\\reactstrap\\es\\UncontrolledNavDropdown.js","original":{"line":4,"column":0}},{"generated":{"line":23,"column":0},"source":"..\\node_modules\\reactstrap\\es\\UncontrolledNavDropdown.js","original":{"line":6,"column":0}},{"name":"UncontrolledNavDropdown","generated":{"line":23,"column":4},"source":"..\\node_modules\\reactstrap\\es\\UncontrolledNavDropdown.js","original":{"line":6,"column":4}},{"generated":{"line":23,"column":30},"source":"..\\node_modules\\reactstrap\\es\\UncontrolledNavDropdown.js","original":{"line":6,"column":30}},{"name":"UncontrolledNavDropdown","generated":{"line":23,"column":39},"source":"..\\node_modules\\reactstrap\\es\\UncontrolledNavDropdown.js","original":{"line":6,"column":39}},{"generated":{"line":23,"column":62},"source":"..\\node_modules\\reactstrap\\es\\UncontrolledNavDropdown.js","original":{"line":6,"column":30}},{"name":"props","generated":{"line":23,"column":63},"source":"..\\node_modules\\reactstrap\\es\\UncontrolledNavDropdown.js","original":{"line":6,"column":63}},{"generated":{"line":23,"column":68},"source":"..\\node_modules\\reactstrap\\es\\UncontrolledNavDropdown.js","original":{"line":6,"column":30}},{"generated":{"line":23,"column":70},"source":"..\\node_modules\\reactstrap\\es\\UncontrolledNavDropdown.js","original":{"line":6,"column":70}},{"generated":{"line":24,"column":0},"source":"..\\node_modules\\reactstrap\\es\\UncontrolledNavDropdown.js","original":{"line":7,"column":2}},{"generated":{"line":24,"column":23},"source":"..\\node_modules\\reactstrap\\es\\UncontrolledNavDropdown.js","original":{"line":7,"column":11}},{"generated":{"line":24,"column":145},"source":"..\\node_modules\\reactstrap\\es\\UncontrolledNavDropdown.js","original":{"line":7,"column":2}},{"generated":{"line":25,"column":0},"source":"..\\node_modules\\reactstrap\\es\\UncontrolledNavDropdown.js","original":{"line":8,"column":2}},{"name":"React","generated":{"line":25,"column":9},"source":"..\\node_modules\\reactstrap\\es\\UncontrolledNavDropdown.js","original":{"line":8,"column":9}},{"name":"createElement","generated":{"line":25,"column":25},"source":"..\\node_modules\\reactstrap\\es\\UncontrolledNavDropdown.js","original":{"line":8,"column":15}},{"generated":{"line":25,"column":38},"source":"..\\node_modules\\reactstrap\\es\\UncontrolledNavDropdown.js","original":{"line":8,"column":9}},{"name":"UncontrolledDropdown","generated":{"line":25,"column":39},"source":"..\\node_modules\\reactstrap\\es\\UncontrolledNavDropdown.js","original":{"line":8,"column":29}},{"generated":{"line":25,"column":69},"source":"..\\node_modules\\reactstrap\\es\\UncontrolledNavDropdown.js","original":{"line":8,"column":9}},{"generated":{"line":25,"column":71},"source":"..\\node_modules\\reactstrap\\es\\UncontrolledNavDropdown.js","original":{"line":8,"column":51}},{"generated":{"line":25,"column":94},"source":"..\\node_modules\\reactstrap\\es\\UncontrolledNavDropdown.js","original":{"line":8,"column":60}},{"name":"nav","generated":{"line":26,"column":0},"source":"..\\node_modules\\reactstrap\\es\\UncontrolledNavDropdown.js","original":{"line":9,"column":4}},{"generated":{"line":26,"column":9},"source":"..\\node_modules\\reactstrap\\es\\UncontrolledNavDropdown.js","original":{"line":9,"column":9}},{"generated":{"line":27,"column":0},"source":"..\\node_modules\\reactstrap\\es\\UncontrolledNavDropdown.js","original":{"line":8,"column":60}},{"generated":{"line":27,"column":3},"source":"..\\node_modules\\reactstrap\\es\\UncontrolledNavDropdown.js","original":{"line":8,"column":51}},{"name":"props","generated":{"line":27,"column":5},"source":"..\\node_modules\\reactstrap\\es\\UncontrolledNavDropdown.js","original":{"line":10,"column":5}},{"generated":{"line":27,"column":10},"source":"..\\node_modules\\reactstrap\\es\\UncontrolledNavDropdown.js","original":{"line":8,"column":51}},{"generated":{"line":27,"column":11},"source":"..\\node_modules\\reactstrap\\es\\UncontrolledNavDropdown.js","original":{"line":8,"column":9}},{"generated":{"line":27,"column":12},"source":"..\\node_modules\\reactstrap\\es\\UncontrolledNavDropdown.js","original":{"line":8,"column":2}},{"generated":{"line":28,"column":0},"source":"..\\node_modules\\reactstrap\\es\\UncontrolledNavDropdown.js","original":{"line":11,"column":1}},{"generated":{"line":28,"column":1},"source":"..\\node_modules\\reactstrap\\es\\UncontrolledNavDropdown.js","original":{"line":6,"column":0}},{"name":"UncontrolledNavDropdown","generated":{"line":30,"column":18},"source":"..\\node_modules\\reactstrap\\es\\UncontrolledNavDropdown.js","original":{"line":13,"column":15}}],"sources":{"..\\node_modules\\reactstrap\\es\\UncontrolledNavDropdown.js":"import _extends from \"@babel/runtime/helpers/esm/extends\";\nimport React from 'react';\nimport { warnOnce } from './utils';\nimport UncontrolledDropdown from './UncontrolledDropdown';\n\nvar UncontrolledNavDropdown = function UncontrolledNavDropdown(props) {\n  warnOnce('The \"UncontrolledNavDropdown\" component has been deprecated.\\nPlease use component \"UncontrolledDropdown\" with nav prop.');\n  return React.createElement(UncontrolledDropdown, _extends({\n    nav: true\n  }, props));\n};\n\nexport default UncontrolledNavDropdown;"},"lineCount":null}},"hash":"936a264caba28cacd930a1e0bb8db028","cacheData":{"env":{}}}